modernqqt/__init__.py
modernqqt/constructor/__init__.py
modernqqt/constructor/initialize.py
modernqqt/resources/Icon.png
modernqqt/resources/Logo.png
modernqqt/resources/__init__.py
modernqqt/resources/ui/angle-down.png
modernqqt/resources/ui/angle-down.svg
modernqqt/src/core/__init__.py
modernqqt/src/core/dialog.py
modernqqt/src/core/exceptions.py
modernqqt/src/core/font.py
modernqqt/src/core/load.py
modernqqt/src/core/stylesheet.py
modernqqt/src/util/__init__.py
modernqqt/src/util/config.py
modernqqt/widgets/__init__.py
modernqqt/widgets/basic/button.py
modernqqt/widgets/basic/groups.py
modernqqt/widgets/basic/label.py
modernqqt/widgets/basic/styles/button.css
modernqqt/widgets/basic/styles/check_box.css
modernqqt/widgets/basic/styles/digital_entry.css
modernqqt/widgets/basic/styles/drop_down_menu.css
modernqqt/widgets/basic/styles/entry.css
modernqqt/widgets/basic/styles/group_box.css
modernqqt/widgets/basic/styles/radio_button.css
modernqqt/widgets/basic/styles/widgets_list.css
modernqqt/widgets/basic/switchers.py
modernqqt/widgets/basic/widgets_list.py
modernqqt/windows/__init__.py
modernqqt/windows/main_window.py
modernqqt/windows/styles/main_window.css
modernqqt-0.1.5.dist-info/LICENSE
modernqqt-0.1.5.dist-info/METADATA
modernqqt-0.1.5.dist-info/WHEEL
modernqqt-0.1.5.dist-info/RECORD
