Metadata-Version: 2.1
Name: ModernQQt
Version: 0.1.5
Summary: ModernQt: A Cutting-Edge GUI Library Built on PyQt6 ModernQt is a intuitive graphical user interface (GUI) library designed to simplify the development of modern, visually stunning, and highly functional applications. Built on the robust foundation of PyQt6. Now ModernQt is in development.
License: MIT
Author: chebupelka8
Author-email: stpzamyatin@gmail.com
Requires-Python: >=3.11,<3.13
Classifier: License :: OSI Approved :: MIT License
Classifier: Programming Language :: Python :: 3
Classifier: Programming Language :: Python :: 3.11
Classifier: Programming Language :: Python :: 3.12
Requires-Dist: pyside6 (>=6.7.0,<7.0.0)
